{
  "tags": {
    "allowUnknownTags" : true
  },
  "plugins": ["plugins/markdown"],

  "templates": {
    "systemName"            : "business-objects v1.0.15",
    "footer"                : "<center>This site is a work in progress. If you find bugs or have feature requests, please <a href=https://github.com/logikum/business-objects/issues>let us know</a>.</center>",
    "copyright"             : "JavaScript business objects ♦ Copyright © 2014-2015 Logikum, Ltd.",
    "navType"               : "vertical",
    "theme"                 : "united",
    "linenums"              : true,
    "collapseSymbols"       : false,
    "inverseNav"            : true,
    "outputSourceFiles"     : false,
    "outputSourcePath"      : false,
    "dateFormat"            : "YYYY. MMMM D.",
    "highlightTutorialCode" : true,
    "syntaxTheme"   		: "default"
  },
  "markdown": {
    "parser"   : "gfm",
    "hardwrap" : true
  }
}
